etherweaver/__init__.py
etherweaver/__main__.py
etherweaver/server_config_loader.py
etherweaver/core_classes/__init__.py
etherweaver/core_classes/appliance.py
etherweaver/core_classes/config_object.py
etherweaver/core_classes/datatypes.py
etherweaver/core_classes/errors.py
etherweaver/core_classes/fabric.py
etherweaver/core_classes/infrastructure.py
etherweaver/core_classes/role.py
etherweaver/core_classes/utils.py
etherweaver/core_classes/test/__init__.py
etherweaver/core_classes/test/test_datatypes.py
etherweaver/core_classes/test/test_infrastructure.py
etherweaver/plugins/__init__.py
etherweaver/plugins/plugin_class.py
etherweaver/plugins/plugin_class_errors.py
etherweaver/plugins/cumulus/__init__.py
etherweaver/plugins/cumulus/cumulus_switch.py
etherweaver/plugins/cumulus/test/__init__.py
etherweaver/plugins/cumulus/test/test_cumulus_switch.py
etherweaver-0.1.1.dev0.dist-info/METADATA
etherweaver-0.1.1.dev0.dist-info/RECORD
etherweaver-0.1.1.dev0.dist-info/WHEEL
etherweaver-0.1.1.dev0.dist-info/entry_points.txt
etherweaver-0.1.1.dev0.dist-info/top_level.txt
