Metadata-Version: 2.1
Name: etherweaver
Version: 0.1.1.dev0
Summary: UNKNOWN
Home-page: https://github.com/graysonhead/etherweaver
Author: Grayson Head
Author-email: grayson@graysonhead.net
License: GPL V3
Platform: UNKNOWN
